Workbook

Sheet Допущения
A1: Допущения расчёта TCO — 100 магазинов, горизонт 3 года
A3: Общие параметры
A4: Число магазинов в расчёте | B4: 100
A5: Стоимость одного FTE поддержки (полная, с налогами), ₽/год | B5: 1200000 | C5: Допущение для кейса, не фактические данные HR
A7: AS-IS — текущая инфраструктура (локальный сервер в магазине)
A8: CapEx на ремонт/замену сервера и кассового ПК, ₽/магазин/год | B8: 15000 | C8: Обусловлено выходом из строя оборудования (см. INC-8433)
A9: Лицензии Windows Server + SQL Server, ₽/магазин/год | B9: 40000
A10: Штат поддержки (Team Store Ops + выездные инженеры), FTE | B10: 10 | C10: Команда перегружена поддержкой легаси (кейс VitaStore)
A11: Выездное обслуживание и простои (инциденты), ₽/магазин/год | B11: 8000
A12: Канал связи, ₽/магазин/год | B12: 18000
A13: Индексация AS-IS: старение инфраструктуры + инфляция, %/год | B13: 0.07 | C13: Рост риска отказов у стареющего парка серверов
A15: TO-BE — целевая облачная архитектура (тонкий клиент + HAL, см. Задание 3)
A16: CapEx: тонкий клиент (Cloud POS) + HAL-устройство, ₽/магазин (единоразово, Год 1) | B16: 60000
A17: Ежегодное обновление парка устройств, % от начального CapEx | B17: 0.05 | C17: С Года 2: частичная замена/ремонт тонких клиентов и HAL
A18: Миграция и внедрение платформы (единоразово, Год 1), ₽ | B18: 10000000 | C18: Разработка HAL-адаптеров, облачного бэкенда, роллаут на 100 магазинов, обучение
A19: Подписка Cloud POS / HAL платформа, ₽/магазин/мес | B19: 3000
A20: Облачная инфраструктура (API GW, Payment Gateway, MDM/PIM, Sync, Managed DB), ₽/год (Год 1) | B20: 2500000
A21: Рост стоимости облачной инфраструктуры, %/год | B21: 0.08 | C21: Рост нагрузки по мере подключения магазинов
A22: Штат поддержки (удалённый мониторинг, без выездов), FTE | B22: 4
A23: Выездное обслуживание (замена устройств), ₽/магазин/год | B23: 1500
A24: Канал связи (основной + резервный для офлайн-режима), ₽/магазин/год | B24: 24000
A25: Индексация TO-BE: подписки/инфраструктура, %/год | B25: 0.05
A27: Все значения на этом листе — иллюстративные допущения для кейса VitaStore (не фактические цены поставщиков). Ячейки с жёлтой заливкой — единственные, которые нужно менять при пересчёте модели.

Sheet TCO_AS-IS
A1: TCO AS-IS на горизонте 3 лет — 100 магазинов
A3: Статья затрат | B3: Год 1 | C3: Год 2 | D3: Год 3 | E3: Итого 3 года
A4: Оборудование (CapEx) | B4: =Допущения!$B$4*Допущения!$B$8 -> 1500000 | C4: =B4*(1+Допущения!$B$13) -> 1605000 | D4: =C4*(1+Допущения!$B$13) -> 1717350 | E4: =B4+C4+D4 -> 4822350
A5: Лицензии / Подписки (OpEx) | B5: =Допущения!$B$4*Допущения!$B$9 -> 4000000 | C5: =B5*(1+Допущения!$B$13) -> 4280000 | D5: =C5*(1+Допущения!$B$13) -> 4579600 | E5: =B5+C5+D5 -> 12859600
A6: Миграция и внедрение (единоразово) | B6: 0 | C6: 0 | D6: 0 | E6: =B6+C6+D6 -> 0
A7: ФОТ поддержки | B7: =Допущения!$B$10*Допущения!$B$5 -> 12000000 | C7: =B7*(1+Допущения!$B$13) -> 12840000 | D7: =C7*(1+Допущения!$B$13) -> 13738800 | E7: =B7+C7+D7 -> 38578800
A8: Выездное обслуживание и инциденты | B8: =Допущения!$B$4*Допущения!$B$11 -> 800000 | C8: =B8*(1+Допущения!$B$13) -> 856000 | D8: =C8*(1+Допущения!$B$13) -> 915920 | E8: =B8+C8+D8 -> 2571920
A9: Каналы связи | B9: =Допущения!$B$4*Допущения!$B$12 -> 1800000 | C9: =B9*(1+Допущения!$B$13) -> 1926000 | D9: =C9*(1+Допущения!$B$13) -> 2060820 | E9: =B9+C9+D9 -> 5786820
A10: Облачная инфраструктура (Payment Gateway, MDM/PIM, Sync, Managed DB) | B10: 0 | C10: 0 | D10: 0 | E10: =B10+C10+D10 -> 0
A11: ИТОГО | B11: =SUM(B4:B10) -> 20100000 | C11: =SUM(C4:C10) -> 21507000 | D11: =SUM(D4:D10) -> 23012490 | E11: =SUM(E4:E10) -> 64619490
A13: Строки «Миграция и внедрение» и «Облачная инфраструктура» относятся только к сценарию TO-BE — в AS-IS таких статей нет (0).

Sheet TCO_TO-BE
A1: TCO TO-BE на горизонте 3 лет — 100 магазинов
A3: Статья затрат | B3: Год 1 | C3: Год 2 | D3: Год 3 | E3: Итого 3 года
A4: Оборудование (CapEx) | B4: =Допущения!$B$4*Допущения!$B$16 -> 6000000 | C4: =Допущения!$B$4*Допущения!$B$16*Допущения!$B$17 -> 300000 | D4: =C4*(1+Допущения!$B$25) -> 315000 | E4: =B4+C4+D4 -> 6615000
A5: Лицензии / Подписки (OpEx) | B5: =Допущения!$B$4*Допущения!$B$19*12 -> 3600000 | C5: =B5*(1+Допущения!$B$25) -> 3780000 | D5: =C5*(1+Допущения!$B$25) -> 3969000 | E5: =B5+C5+D5 -> 11349000
A6: Миграция и внедрение (единоразово) | B6: =Допущения!$B$18 -> 10000000 | C6: 0 | D6: 0 | E6: =B6+C6+D6 -> 10000000
A7: ФОТ поддержки | B7: =Допущения!$B$22*Допущения!$B$5 -> 4800000 | C7: =B7*(1+Допущения!$B$25) -> 5040000 | D7: =C7*(1+Допущения!$B$25) -> 5292000 | E7: =B7+C7+D7 -> 15132000
A8: Выездное обслуживание и инциденты | B8: =Допущения!$B$4*Допущения!$B$23 -> 150000 | C8: =B8*(1+Допущения!$B$25) -> 157500 | D8: =C8*(1+Допущения!$B$25) -> 165375 | E8: =B8+C8+D8 -> 472875
A9: Каналы связи | B9: =Допущения!$B$4*Допущения!$B$24 -> 2400000 | C9: =B9*(1+Допущения!$B$25) -> 2520000 | D9: =C9*(1+Допущения!$B$25) -> 2646000 | E9: =B9+C9+D9 -> 7566000
A10: Облачная инфраструктура (Payment Gateway, MDM/PIM, Sync, Managed DB) | B10: =Допущения!$B$20 -> 2500000 | C10: =B10*(1+Допущения!$B$21) -> 2700000 | D10: =C10*(1+Допущения!$B$21) -> 2916000 | E10: =B10+C10+D10 -> 8116000
A11: ИТОГО | B11: =SUM(B4:B10) -> 29450000 | C11: =SUM(C4:C10) -> 14497500 | D11: =SUM(D4:D10) -> 15303375 | E11: =SUM(E4:E10) -> 59250875
A13: Строка «Миграция и внедрение» — единоразовые затраты Года 1 на разработку платформы и роллаут на 100 магазинов.

Sheet ROI
A1: ROI и точка безубыточности миграции (Break-even)
A3: Показатель | B3: Год 1 | C3: Год 2 | D3: Год 3
A4: Итого AS-IS, ₽ | B4: ='TCO_AS-IS'!B11 -> 20100000 | C4: ='TCO_AS-IS'!C11 -> 21507000 | D4: ='TCO_AS-IS'!D11 -> 23012490
A5: Итого TO-BE, ₽ | B5: ='TCO_TO-BE'!B11 -> 29450000 | C5: ='TCO_TO-BE'!C11 -> 14497500 | D5: ='TCO_TO-BE'!D11 -> 15303375
A6: Экономия за год (AS-IS − TO-BE), ₽ | B6: =B4-B5 -> -9350000 | C6: =C4-C5 -> 7009500 | D6: =D4-D5 -> 7709115
A7: Накопленный AS-IS, ₽ | B7: =B4 -> 20100000 | C7: =B7+C4 -> 41607000 | D7: =C7+D4 -> 64619490
A8: Накопленный TO-BE, ₽ | B8: =B5 -> 29450000 | C8: =B8+C5 -> 43947500 | D8: =C8+D5 -> 59250875
A9: Накопленный эффект (AS-IS − TO-BE), ₽ | B9: =B7-B8 -> -9350000 | C9: =C7-C8 -> -2340500 | D9: =D7-D8 -> 5368615
A11: Точка безубыточности, месяцев от старта проекта | B11: =IF(B9>=0, 0, IF(C9>=0, 12+12*(-B9)/C6, IF(D9>=0, 24+12*(-C9)/D6, "не окупается за 3 года"))) -> 27.64322
A12: Точка безубыточности, лет | B12: =IFERROR(B11/12, "—") -> 2.3036016
A14: Дополнительные инвестиции в Год 1 (TO-BE − AS-IS), ₽ | B14: =B5-B4 -> 9350000
A15: Чистая экономия за 3 года, ₽ | B15: ='TCO_AS-IS'!E11-'TCO_TO-BE'!E11 -> 5368615
A16: ROI за 3 года (чистая экономия / доп. инвестиции Года 1), % | B16: =IFERROR(B15/B14, "—") -> 0.57418342
A18: Точка безубыточности рассчитана в предположении равномерного распределения затрат внутри года. Поскольку миграционный CapEx и внедрение фактически приходятся на начало Года 1, реальная точка безубыточности может сместиться на 1–2 месяца позже расчётной.
